jspython_pkg/__init__.py
jspython_pkg_vectr0-0.0.1.dist-info/LICENSE
jspython_pkg_vectr0-0.0.1.dist-info/METADATA
jspython_pkg_vectr0-0.0.1.dist-info/WHEEL
jspython_pkg_vectr0-0.0.1.dist-info/top_level.txt
jspython_pkg_vectr0-0.0.1.dist-info/RECORD
