Metadata-Version: 2.1
Name: jspython-pkg-vectr0
Version: 0.0.1
Summary: Python, but JavaScript
Home-page: https://github.com/netriza/jspython
Author: Vectr0 (Ayzan, VectorEngine)
Author-email: ayzan@netriza.ml
License: UNKNOWN
Platform: UNKNOWN
Classifier: Programming Language :: Python :: 3
Classifier: License :: OSI Approved :: MIT License
Classifier: Operating System :: OS Independent
Requires-Python: >=3.6
